[{"id":0,"href":"/de/docs/using-regolith/first-launch/","title":"Erster Start","section":"Docs","content":"Erster Start #   Die Standardoberfläche von Regolith enthält keine visuellen Hinweise darauf, wie man Anwendungen startet oder andere gängige Aufgaben ausführt. Dies kann beim ersten Mal etwas verwirrend sein. Die Verwendung der Regolith-Benutzeroberfläche ist jedoch relativ einfach, wenn man sich nur die folgenden zwei Tastenkombinationen merkt:\n   Aktion Tastenkombination Zweck     Keybinding Viewer  super shift ?   Verfügbare Keybindings anzeigen und ausführen   App Launcher  super space   Starten einer Desktop-Anwendung    Die Super-Taste #  Die meisten Tastenkombinationen, die Sie mit Regolith verwenden werden, beginnen mit der Taste super  . Auf dieser Taste steht in der Regel \u0026ldquo;WIN\u0026rdquo; oder es ist ein MS-Windows-Logo abgebildet. Auf einem Mac ist es die Befehlstaste ⌘  -Taste. In Zukunft wird diese Taste einfach als super  bezeichnet, aber denken Sie daran, dass Sie die physische Taste super  in Ihrer Konfiguration ändern können, wenn Sie das möchten.\n Wenn Sie eine dieser Tastenkombinationen eingeben, wird ein Startdialog auf dem fokussierten Monitor angezeigt. Beide Dialoge verhalten sich gleich:\n   Der Dialog hat oben ein Texteingabe-Widget, gefolgt von einem Auswahl-Widget. Das allgemeine Nutzungsmuster für diese Dialoge ist die Auswahl eines Elements aus der angezeigten Liste. Beginnen Sie zu tippen, um die Auswahl zu filtern, und verwenden Sie die Pfeiltasten, um eine Auswahl zu treffen. Durch Drücken von Enter  wird das ausgewählte Element aktiviert. Bei Tastenkombinationen bedeutet dies, dass eine Tastenkombination manuell ausgeführt wird. Bei Anwendungen wird die ausgewählte Anwendung gestartet.\nKeybinding-Viewer #  Der Zweck des Keybinding Viewers ist es, das Auffinden und Erlernen der Regolith-Keybindings schnell und einfach zu machen. Eine Referenz zu den Keybindings ist auf dieser Seite verfügbar, aber es ist schneller, einfach den Dialog aufzurufen und nach der gewünschten Aktion zu suchen. Einmal gefunden, kann die Tastenkombination entweder über die Tastatur oder durch Auswahl des Elements im Dialogfeld ausgeführt werden.\nAnwendungsstarter #  Eine grundlegende Aufgabe jeder Desktop-Umgebung ist es, den Benutzern das Starten von Anwendungen zu ermöglichen. In Regolith wird dies über den Anwendungsstarter-Dialog realisiert. Wie bei den Tastenkombinationen zeigt der Dialog zunächst eine Liste aller verfügbaren Desktop-Anwendungen an. Beginnen Sie zu tippen, um die Auswahl zu filtern und verwenden Sie die Pfeiltasten, um eine bestimmte Auswahl zu treffen. Drücken Sie Enter  , um die ausgewählte Anwendung zu starten.\nNächste Schritte #  Werfen Sie einen Blick auf die Seite basics, um mehr über die Regolith-Schnittstelle zu erfahren.\n"},{"id":1,"href":"/de/docs/reference/configurations/","title":"Config Files","section":"Docs","content":"   Component Default Config User Config Notes     i3 / i3-gaps /etc/regolith/i3/config ~/.config/regolith2/i3/config (global override) i3 config partials live in /usr/share/regolith/i3/config.d   Xresources /usr/share/regolith-look/default ~/.config/regolith2/Xresources ~/.Xresources is also loaded but intended for properties that may also be required in other desktop sessions.   Bar status indicators /usr/share/i3xrocks/conf.d/ ~/.config/regolith2/i3xrocks/conf.d Each block has it\u0026rsquo;s own file. Filename determines ordering.   Picom (Compton) Compositor /etc/regolith/picom/config ~/.config/regolith2/picom/config     NOTE: Adding an i3 config file in ~/.config/regolith2/i3/config will essentially override all Regolith configuration including Xresources and looks.  "},{"id":2,"href":"/de/docs/using-regolith/basics/","title":"Grundlegende Verwendung","section":"Docs","content":"Während wir in anderen Bereichen der Dokumentation alles detaillierter behandeln werden, deckt diese Seite die grundlegende Verwendung von Regolith ab.\nVerwendung #  Starten einer Anwendung #  Nach der ersten Anmeldung enthält der Bildschirm eine Leiste am unteren Rand und einige Tastaturkürzel in einem Dialog. Dieser Dialog soll dem Benutzer helfen, Tastenkombinationen für verschiedene Aktionen in der Desktop-Umgebung zu finden und zu speichern. Er kann mit der Taste esc verlassen und mit super shift ?  . Um eine Anwendung zu starten, drücken Sie super space  und ein ähnlicher Dialog wird mit den auf dem System installierten Anwendungen geladen. Wenn Sie beginnen, den Namen der Anwendung, die Sie starten möchten, einzugeben, wird die Liste auf die passenden Anwendungen eingeschränkt. Sie können auch mit den Pfeiltasten durch die Liste blättern.\nZu einem Fenster navigieren #  Um eine laufende Anwendung zu fokussieren, kann die super ctrl space  Tastenkombination verwendet werden, um einen Dialog mit allen laufenden Fenstern anzuzeigen. Wählen Sie einfach das gewünschte Fenster aus, und das System wechselt in den Arbeitsbereich des Fensters und aktiviert dessen Fokus.\nEinen neuen Arbeitsbereich erstellen #  Arbeitsbereiche (in manchen Desktop-Umgebungen auch als \u0026ldquo;virtuelle Desktops\u0026rdquo; bezeichnet) sind eine der wichtigsten Möglichkeiten, um Fenster zu verwalten. Jeder Arbeitsbereich bietet einen Bildschirm für einen unabhängigen Satz von Fenstern. Um einen Arbeitsbereich zu erstellen oder zu einem bestehenden Arbeitsbereich zu navigieren, geben Sie seinen Index mit den Tasten super 0-9  an.\nSuchen und Starten einer Datei #  Die Suche nach einer bestimmten Datei auf Ihrem lokalen Computer kann auf verschiedene Weise erfolgen. Regolith bietet einen Dateisuchdialog über super alt space  zum schnellen Suchen und optionalen Laden einer Datei mit seiner Standardanwendung. Durch Drücken der Eingabetaste bei einer Auswahl wird die Datei mit dem Befehl xdg-open aufgerufen.\nTerminal #  Das Terminal ist eine spezielle Anwendung, die ihre eigene Tastenkombination hat, super enter  .\nBrowser #  Der bevorzugte Browser ist ebenfalls eine spezielle Anwendung und kann mit super shift enter  gestartet werden.\nBeenden einer Anwendung #  Mit super shift q  wird die fokussierte Anwendung beendet. Bei fehlerhaften Anwendungen wird super alt q  das Beenden der fokussierten Anwendung erzwingen, aber beachten Sie, dass ungespeicherte Daten verloren gehen können.\nArbeitsbereiche wechseln #  Eine primäre Möglichkeit, die Belegung des Bildschirms durch Anwendungen zu verwalten, ist die Verwendung von Arbeitsbereichen (Workspaces). Ein Arbeitsbereich ist im Wesentlichen eine Gruppe von null oder mehr Anwendungen, die alle Fenster auf demselben virtuellen Bildschirm darstellen. Benutzer können zwischen Arbeitsbereichen wechseln, um mehr Platz für Anwendungen zu gewinnen. Fenster können zwischen Arbeitsbereichen verschoben werden. Arbeitsbereiche können an eine physische Anzeige gebunden sein oder nach Bedarf auf andere Anzeigen verschoben werden. Um den Arbeitsbereich zu wechseln, halten Sie die Taste super  gedrückt und drücken Sie eine der Zifferntasten. Dadurch wird zu diesem Arbeitsbereich navigiert. Wenn in einem bestimmten Arbeitsbereich ein Fenster vorhanden ist, wird es in der Leiste als aktiv angezeigt. So kann der Benutzer anhand der Leiste erkennen, in welchen Arbeitsbereichen sich aktive Anwendungen befinden.\nArbeitsbereiche können auch mit super tab  und super shift tab  vor- und zurückgeblättert werden.\nDas System konfigurieren #  Die Einstellungs-App (auch bekannt als regolith-control-center) ist die primäre Schnittstelle für allgemeine Konfigurationsaufgaben, wie die Konfiguration von WiFi und Bluetooth, die Konfiguration von App-Zuordnungen und die Einrichtung von Benutzern. Die App kann über die super c  Tastenkombination oder vom Launcher aus über die App Regolith Settings gestartet werden.\nTastenkombinationen anzeigen #  Alle vom Regolith-Desktop verwendeten Tastenkombinationen können mit ilia eingesehen, sortiert und ausgeführt werden. Dieser Dialog wird mit super shift ?  aktiviert.\nVerwalten von Benachrichtigungen #  Das Desktop-Benachrichtigungssystem von Regolith wurde entwickelt, um Pop-ups zu verhindern, die den Benutzer von seiner Arbeit ablenken könnten. Benachrichtigungen können über super n  eingesehen und verwaltet werden. Spezielle Tastenkombinationen, wie z.B. das Löschen einer oder mehrerer Benachrichtigungen, finden Sie auf der Registerkarte \u0026ldquo;Hilfe\u0026rdquo; des Dialogs. Für Benutzer, die eine bessere Sichtbarkeit der aktuellen Benachrichtigungen wünschen, kann der Statusindikator i3xrocks-rofication über den Systempaketmanager installiert werden. Damit wird die Anzahl der kritischen und normalen ungelesenen Benachrichtigungen in der Leiste angezeigt.\n"},{"id":3,"href":"/de/docs/using-regolith/configuration/","title":"Konfiguration","section":"Docs","content":"Empfohlene Pakete für neue Benutzer #  Looks #  Installieren Sie alle offiziellen Regolith-Looks:\nsudo apt install regolith-look-* Status-Indikatoren #  Das folgende Snippet installiert Statusindikatoren-Pakete, die für neue Benutzer empfohlen werden:\nsudo apt install i3xrocks-focused-window-name i3xrocks-rofication i3xrocks-info i3xrocks-app-launcher i3xrocks-memory Um einen dieser Indikatoren später zu entfernen, deinstallieren Sie ihn einfach von Ihrem System. Beispiel:\nsudo apt remove i3xrocks-info Laptop-Akkustatus #  Zeigt den aktuellen Batteriestatus eines Laptops an:\nsudo apt install i3xrocks-battery Hintergrundbild #  Die meisten Regolith Looks bieten eine Standard-Desktop-Farbe oder ein Bild. Das Hintergrundbild kann durch Angabe des Pfades zum Hintergrundbild über den Xresources-Parameter regolith.wallpaper.file festgelegt werden.\nBeispiel: Angenommen, die Datei /usr/share/backgrounds/hardy_wallpaper_uhd.png ist vorhanden:\necho \u0026quot;regolith.wallpaper.file: /usr/share/backgrounds/hardy_wallpaper_uhd.png\u0026quot; \u0026gt;\u0026gt; ~/.config/regolith2/Xresources regolith-look refresh Um die Darstellung (Zoom, Skalierung, etc.) des Hintergrundbildes zu ändern, setzen Sie regolith.wallpaper.options. Optionen sind: none, wallpaper, centered, scaled, stretched, zoom, spanned\nBeispiel:\necho \u0026quot;regolith.wallpaper.options: zoom\u0026quot; \u0026gt;\u0026gt; ~/.config/regolith2/Xresources regolith-look refresh Um eine Farbe anstelle eines Bildes anzugeben, verwenden Sie den Xresource-Parameter regolith.wallpaper.color.primary:\necho \u0026quot;regolith.wallpaper.file: \u0026quot; \u0026gt;\u0026gt; ~/.config/regolith2/Xresources echo \u0026quot;regolith.wallpaper.color.primary: blue\u0026quot; \u0026gt;\u0026gt; ~/.config/regolith2/Xresources regolith-look refresh Um eine sekundäre Farbe und einen Farbverlauf zu definieren:\necho \u0026quot;regolith.wallpaper.file: \u0026quot; \u0026gt;\u0026gt; ~/.config/regolith2/Xresources echo \u0026quot;regolith.wallpaper.color.primary: blue\u0026quot; \u0026gt;\u0026gt; ~/.config/regolith2/Xresources echo \u0026quot;regolith.wallpaper.color.secondary: green\u0026quot; \u0026gt;\u0026gt; ~/.config/regolith2/Xresources echo \u0026quot;regolith.wallpaper.color.shading.type: vertical\u0026quot; \u0026gt;\u0026gt; ~/.config/regolith2/Xresources regolith-look refresh Sperrbildschirm-Hintergrundbild #  Das Hintergrundbild des Sperrbildschirms kann auf die gleiche Weise wie das Desktop-Hintergrundbild verwaltet werden. Die Parameter sind die gleichen wie beim Desktop-Hintergrundbild, aber mit dem Präfix lockscreen vor wallpaper, etwa so: regolith.lockscreen.wallpaper.... Um zum Beispiel ein Bild für den Sperrbildschirm anzugeben:\necho \u0026quot;regolith.lockscreen.wallpaper.file: /usr/share/backgrounds/hardy_wallpaper_uhd.png\u0026quot; \u0026gt;\u0026gt; ~/.config/regolith2/Xresources regolith-look refresh Deaktivieren der Wallpaper-Verwaltung #  Wenn Sie das Hintergrundbild außerhalb von Regolith verwalten möchten, geben Sie einfach leere Werte für das Hintergrundbild und die Farbe an:\necho \u0026quot;regolith.wallpaper.file: \u0026quot; \u0026gt;\u0026gt; ~/.config/regolith2/Xresources echo \u0026quot;regolith.wallpaper.color.primary: \u0026quot; \u0026gt;\u0026gt; ~/.config/regolith2/Xresources Statusleisten-Anzeigen #  Statusanzeigen wie CPU-Auslastung, Datum und Uhrzeit, Benachrichtigungen, Wetter und andere Systeminformationen können durch die Installation von Paketen hinzugefügt oder entfernt werden. Um zum Beispiel eine Statusanzeige für die Batterie Ihres Laptops anzuzeigen, führen Sie einfach sudo apt install i3xrocks-battery aus und aktualisieren Sie dann die Sitzung mit regolith-look refresh. Um herauszufinden, welche Indikatoren verfügbar sind, führen Sie apt search ^i3xrocks- aus oder suchen Sie nach i3xrocks- in Ihrer bevorzugten Paketmanager-GUI, wie zum Beispiel Synaptic. Es gibt weitere Dokumentation für die Konfiguration von Statusanzeigen, auch \u0026ldquo;blocklets\u0026rdquo; genannt.\nLooks #  Farben, Hintergrundbilder, Fenster- und Leistenlayouts und andere visuelle Faktoren werden in Regolith gebündelt und als \u0026ldquo;Looks\u0026rdquo; bezeichnet. Looks bieten eine einfache Möglichkeit, das gesamte Aussehen des Desktops zu ändern. Wie die Statusleistenindikatoren werden auch die Looks in Paketen zusammengefasst und wie jedes andere Softwarepaket installiert und entfernt. Look-Pakete haben das folgende Namensformat: regolith-look-\u0026lt;name\u0026gt;. Um nach verfügbaren Looks zu suchen, kann apt oder ein GUI-Paketmanager verwendet werden. Zur Auswahl eines installierten Looks wird mit der Tastenkombination super alt l  ein Dialog angezeigt:\nAlternativ kann der Terminalbefehl regolith-look verwendet werden, um das Aussehen zu ändern und die aktive Sitzung mit dem ausgewählten Aussehen zu aktualisieren. Hier ist ein Beispiel, das zum gruvbox-Look wechselt:\napt search ^regolith-look- [...] regolith-look-gruvbox/unknown,now 0.4.6-1regolith amd64 [...] sudo apt install regolith-look-gruvbox regolith-look set gruvbox regolith-look refresh Um einfach alle verfügbaren Looks zu installieren:\nsudo apt install regolith-look-* i3 Features #  Seit Regolith 2.0 werden viele Aspekte der i3-Konfiguration über den Paketmanager verwaltet. Mit i3 4.20 wurde die Möglichkeit eingeführt, Include-Dateien als Teil der Konfiguration anzugeben. Regolith stellt seine gesamte i3-Konfiguration über diese Dateien bereit, die auch \u0026ldquo;config partials\u0026rdquo; genannt werden. Diese Pakete installieren ihre i3-Konfigurationspartials in /usr/share/regolith/i3/config.d. Durch das Installieren und Entfernen von Paketen kann die i3-Konfiguration an die eigenen Vorlieben angepasst werden, während gleichzeitig die Upstream-Änderungen für Aspekte der Konfiguration, die sich nicht ändern müssen, unverändert bleiben können. Wenn das Paket regolith-desktop installiert wird, werden diese Konfigurationselemente standardmäßig auch als Soft-Dependencies installiert:\n   Paket Funktion     regolith-i3-base-launchers Terminal und Browser starten   regolith-i3-default-style Fensterverhalten   regolith-i3-navigation Navigationstastenbelegung   regolith-i3-networkmanager Netzwerk- und WiFi-Funktionen   regolith-i3-next-workspace Arbeitsbereich-Dienstprogramm   regolith-i3-resize Tastaturbelegung Größenänderung   regolith-i3-session Tastaturbelegung Session   regolith-i3-unclutter Mauszeiger ausblenden, wenn er nicht benutzt wird   regolith-i3-user-programs Optionales Starten von Benutzerprogrammen, die in Xresources angegeben sind   regolith-i3-workspace-config Tastaturbelegung des Arbeitsbereichs    Soft-Abhängigkeiten können entfernt werden, ohne dass Pakete entfernt werden, die davon abhängen. Dies bedeutet, dass jedes der aufgelisteten Pakete entfernt werden kann. Benutzer können Änderungen an der Konfiguration auf solidere Weise vornehmen, indem sie einen Teil der Standardkonfiguration durch ihre eigene Version ersetzen. Dies kann erreicht werden, indem man den Teil, der angepasst werden soll, nach ~/.config/regolith2/i3/config.d/ kopiert und die Originaldatei in /usr/share/regolith/i3/config.d über apt entfernt. Zum Beispiel, um die Tastaturbelegung des Arbeitsbereichs anzupassen:\nmkdir -p ~/.config/regolith2/i3/config.d cp /usr/share/regolith/i3/config.d/40_workspace-config ~/.config/regolith2/i3/config.d/ vim ~/.config/regolith2/i3/config.d/40_workspace-config # gewünschte Änderungen vornehmen sudo apt remove regolith-i3-workspace-config # Entfernt die Standardversion # Starte i3 neu oder logge dich wieder ein Auf diese Weise können die unveränderten Teilkonfigurationen weiterhin Updates und Fehlerbehebungen erhalten, ohne die benutzerspezifische Konfiguration zu beeinflussen.\nAlle i3-Konfigurationspakete #  Im Folgenden finden Sie eine Liste aller i3-Konfigurationspakete, die in Regolith 2.0 verfügbar sind:\n   Paket Funktion     regolith-i3-base-launchers Terminal und Browser starten   regolith-i3-compositor Compositor-Integration (delegiert an regolith-compositor-\u0026lt;variant\u0026gt;)   regolith-i3-default-style Fensterverhalten   regolith-i3-ftue Hilfe für neue User   regolith-i3-gaps-partial i3-gaps Konfiguration (wenn installiert, ersetzt i3-gaps i3)   regolith-i3-gnome Regolith-Einstellungen   regolith-i3-i3xrocks Konfiguration der i3-Balkenstatusanzeigen   regolith-i3-ilia ilia Einbindung   regolith-i3-navigation Tastaturbelegung für die Navigation   regolith-i3-networkmanager \u0026ldquo;netzwerk-manager\u0026rdquo;-Einbindung   regolith-i3-next-workspace Funktion zum automatischen Erstellen des nächsten Arbeitsbereichs   regolith-i3-remontoire Integration der Ansicht \u0026ldquo;Legacy keybindings\u0026rdquo;   regolith-i3-resize Tastaturbelegung für Größenänderung   regolith-i3-rofi Integration des alten Desktop-Startprogramms   regolith-i3-rofication Integration der alten Benachrichtigungsanzeige   regolith-i3-rofication-ilia Integration der Benachrichtigungsanzeige   regolith-i3-session Tastaturbelegung der Session   regolith-i3-snapshot i3-Arbeitsbereichspersistenz   regolith-i3-unclutter Ausblenden der Maus bei Nichtgebrauch   regolith-i3-user-programs Optionaler Start von Benutzerprogrammen, die in Xresources angegeben sind   regolith-i3-workspace-config Arbeitsbereich-Tastaturbelegung    Tastaturbelegungen #  Die häufigste Änderung der Tastaturbelegung ist die Taste super  . Regolith verwendet Xresources als kanonische Quelle für Einstellungen, die von verschiedenen UI-Komponenten gelesen werden. Die Tabelle der Xresources -Parameter, für die Benutzerkonfiguration ist an anderer Stelle verfügbar. Um die Tastaturbelegung super  von der Taste \u0026ldquo;windows\u0026rdquo; auf \u0026ldquo;alt\u0026rdquo; zu ändern, fügen Sie die folgende Zeilen in die Datei ~/.config/regolith2/Xresources ein:\ni3-wm.mod: Mod1 i3-wm.alt: Mod4 Anmerkung: GNOME hat auch seinen eigenen Satz von Tastaturbelegungen. Wenn die Regolith-Sitzung zum ersten Mal initialisiert wird, werden die kollidierenden GNOME-Tastaturbelegungen aus den Benutzereinstellungen entfernt. GNOME-Tastaturbelegungen können in der Regolith-Einstellungs-App verwaltet werden.\nSystemverwaltung #  Die App regolith-control-center ist das Werkzeug zum Konfigurieren von Gebietsschema, Datum, Anzeigen, Netzwerk und verschiedenen anderen Einstellungen. Starten Sie sie über den App-Launcher mit super space  , geben Sie settings ein und drücken Sie Enter, um die App zu starten. Die direkte Tastaturbelegung ist super c  . Die Anwendung kann auch von einem Terminal mit dem Befehl regolith-control-center gestartet werden.\nWeitere Lektüre #  Wenn Sie tiefer einsteigen wollen, finden Sie die verfügbaren Howtos oder lesen Sie die Xresources reference. Werden Sie ein i3-Poweruser, indem Sie das Benutzerhandbuch lesen.\n"},{"id":4,"href":"/de/docs/howtos/","title":"How To","section":"Docs","content":"NOTICE: This page was copied from the Regolith 1.x website and has not been updated for Regolith 2. It may contain out of date information.  More examples and tutorials are available in the regolith-desktop wiki on GitHub.  Using the Terminal #  This section provides examples of how to change Regolith to suit your needs. Most of them will specify commands to be run in the terminal. If using the terminal is new to you or you\u0026rsquo;d just like to refresh your memory, this guide from Ubuntu is recommended. Another tutorial from linuxcommand.org goes into some more advanced territory.\ni3-wm User Guide #  In addition to general command-line abilities, having a basic understanding of what options are available in the i3 user guide is recommended to get the most out of the interface.\n"},{"id":5,"href":"/de/docs/reference/xresources/","title":"Xresources","section":"Docs","content":"   Xresources Key Description     gtk.theme_name GTK Theme   gtk.icon_theme_name GTK Icon Theme   gnome.terminal.audible-bell Enables audible bell in gnome-terminal (true / false)   gtk.document_font_name GTK Document Font Name   gtk.font_name General purpose font for GTK apps and the desktop   gtk.monospace_font_name Font for monospace areas such as i3bar and the terminal   gnome.terminal.background-transparency-percent Background transparency value for gnome-terminal (0 - 100). See also gnome.terminal.use-transparent-background.   gnome.terminal.font Font definition for gnome-terminal   gnome.terminal.scrollbar Flag to enable/disable scrollbar (never / always)   gnome.terminal.use-transparent-background Enables transparent background in gnome-terminal (true / false). See also gnome.terminal.background-transparency-percent.   gnome.wallpaper GNOME Wallpaper (can be overridden in Settings)   gnome.wm.theme GNOME Window Manager Theme (unused)   i3-wm.alt Key mapping for Alt key. See the i3 User Guide for details.   i3-wm.bar.background.color Bar Background Color   i3-wm.bar.position Bar Screen Position   i3-wm.bar.separator.color Color of seperator between blocks   i3-wm.bar.statusline.color    i3-wm.bar.trayoutput Enable or disable the app tray in i3bar   i3-wm.bar.workspace.active.background.color    i3-wm.bar.workspace.active.border.color    i3-wm.bar.workspace.active.text.color    i3-wm.bar.workspace.focused.background.color    i3-wm.bar.workspace.focused.border.color    i3-wm.bar.workspace.focused.text.color    i3-wm.bar.workspace.inactive.background.color    i3-wm.bar.workspace.inactive.border.color    i3-wm.bar.workspace.inactive.text.color    i3-wm.bar.workspace.urgent.background.color    i3-wm.bar.workspace.urgent.border.color    i3-wm.bar.workspace.urgent.text.color    i3-wm.client.focused.color.background    i3-wm.client.focused.color.border    i3-wm.client.focused.color.child_border    i3-wm.client.focused.color.indicator    i3-wm.client.focused.color.text    i3-wm.client.focused_inactive.color.background    i3-wm.client.focused_inactive.color.border    i3-wm.client.focused_inactive.color.child_border    i3-wm.client.focused_inactive.color.indicator    i3-wm.client.focused_inactive.color.text    i3-wm.client.unfocused.color.background    i3-wm.client.unfocused.color.border    i3-wm.client.unfocused.color.child_border    i3-wm.client.unfocused.color.indicator    i3-wm.client.unfocused.color.text    i3-wm.client.urgent.color.background    i3-wm.client.urgent.color.border    i3-wm.client.urgent.color.child_border    i3-wm.client.urgent.color.indicator    i3-wm.client.urgent.color.text    i3-wm.floatingwindow.border.size Window border size in pixels for floating windows   i3-wm.font Window manager font   i3-wm.gaps.inner.size Default gap size between windows in pixels   i3-wm.gaps.outer.size Default gap size at screen edge in pixels   i3-wm.mod Key mapping for Super key. See the i3 User Guide for details.   i3-wm.window.border.size Default border size in pixels   i3-wm.workspace.01.name .. i3-wm.workspace.19.name Workspace Labels   i3-wm.workspace.01.key .. i3-wm.workspace.10.key Workspace Shortucts   i3xrocks.action.volume.left Command to execute when volume indicator is left clicked (default: none)   i3xrocks.action.volume.middle Command to execute when volume indicator is middle clicked (default: none)   i3xrocks.action.volume.right Command to execute when volume indicator is right clicked (default: mute through amixer)   i3xrocks.action.volume.scrollup Command to execute when scroll wheel up is used on volume indicator (default: increase volume through amixer)   i3xrocks.action.volume.scrolldn Command to execute when scroll wheel down is used on volume indicator (default: decrease volume through amixer)   i3xrocks.error.color Color for bar module in error mode   i3xrocks.label.battery0 Bar icon glyph   i3xrocks.label.battery100 Bar icon glyph   i3xrocks.label.battery20 Bar icon glyph   i3xrocks.label.battery50 Bar icon glyph   i3xrocks.label.battery80 Bar icon glyph   i3xrocks.label.batteryac Bar icon glyph   i3xrocks.label.batterycharging Bar icon glyph   i3xrocks.label.batteryunknown Bar icon glyph   i3xrocks.label.capslock Bar icon glyph   i3xrocks.label.color Bar icon glyph   i3xrocks.label.cpu Bar icon glyph   i3xrocks.label.disk Bar icon glyph   i3xrocks.label.dn Bar icon glyph   i3xrocks.label.help Bar icon glyph   i3xrocks.label.mediapaused Bar icon glyph   i3xrocks.label.mediaplaying Bar icon glyph   i3xrocks.label.memory Bar icon glyph   i3xrocks.label.mute Bar icon glyph   i3xrocks.label.notify.error Bar icon glyph   i3xrocks.label.notify.none Bar icon glyph   i3xrocks.label.notify.some Bar icon glyph   i3xrocks.label.numlock Bar icon glyph   i3xrocks.label.off Bar icon glyph   i3xrocks.label.on Bar icon glyph   i3xrocks.label.sound Bar icon glyph   i3xrocks.label.thermometer Bar icon glyph   i3xrocks.label.time Bar icon glyph   i3xrocks.label.up Bar icon glyph   i3xrocks.label.wifi Bar icon glyph   i3xrocks.label.wired Bar icon glyph   i3xrocks.nominal Default bar icon color   i3xrocks.value.color Color of numerical value in bar module   i3xrocks.value.font Font for numerical value in bar module   i3xrocks.warning Warning color for bar module    Optional Xresources keys #  The following Xresources keys are undefined by default but can be used by users to change behavior as desired.\n   Xresources Key Description     i3-wm.gaps.focus_follows_mouse The window under the mouse has focus if enabled   i3-wm.program.launcher.app Command i3 executes from the app launcher keybinding   i3-wm.program.launcher.cmd Command i3 executes from the command launcher keybinding   i3-wm.program.launcher.window Command i3 executes for the window navigation keybinding   i3-wm.program.help Command to launch from the help keybinding   i3-wm.program.file_search Command to launch from the file search keybinding   i3-wm.program.refresh_ui Command to launch from the session refresh keybinding   i3-wm.program.logout Command to launch from the logout keybinding   i3-wm.program.reboot Command to launch from the reboot keybinding   i3-wm.program.shutdown Command to launch from the shutdown keybinding   i3-wm.program.lock Command to launch from the lock screen keybinding   i3-wm.program.sleep Command to launch from the sleep keybinding   i3-wm.program.settings Command to launch from the Control Panel keybinding   i3-wm.program.display Command to launch from the Display Settings keybinding   i3-wm.program.wifi Command to launch from the Wifi Settings keybinding   i3-wm.program.bluetooth Command to launch from the Bluetooth Settings keybinding   i3-wm.program.files Command to launch from the file browser keybinding   i3-wm.program.notification_ui Command to launch from the notification UI keybinding   i3-wm.program.1\u0026hellip;i3-wm.program.3 Optional programs to start with i3   i3xrocks.media-player.player-args Optional arguments used by the media-player i3xrocks block. These arguments are fed straight into playerctl, eg. setting this value to -p spotify only makes the bar display/control spotify.   i3xrocks.action.mic.left Optional command to run on left button click of microphone status indicator.   i3xrocks.action.mic.middle Optional command to run on middle button click of microphone status indicator.   i3xrocks.action.mic.right Override command to run on right button click of microphone status indicator.   i3xrocks.action.mic.scrollup Override command to run on scroll up of microphone status indicator.   i3xrocks.action.mic.scrolldn Override command to run on scroll down of microphone status indicator.   i3xrocks.action.volume.left Optional command to run on left button click of microphone status indicator.   i3xrocks.action.volume.middle Optional command to run on middle button click of microphone status indicator.   i3xrocks.action.volume.right Override command to run on right button click of microphone status indicator.   i3xrocks.action.volume.scrollup Override command to run on scroll up of microphone status indicator.   i3xrocks.action.volume.scrolldn Override command to run on scroll down of microphone status indicator.   i3xrocks.action.disk-capacity Override command to run on disk capacity status indicator.   i3xrocks.action.cpu-usage Override command to run on cpu usage status indicator.   i3xrocks.action.memory Override command to run on memory status indicator.   i3xrocks.action.wifi Override command to run on wifi status indicator.   i3xrocks.action.weather Override command to run on weather status indicator.   i3xrocks.action.media-player.left Optional command to run on left button click of media player status indicator.   i3xrocks.action.media-player.middle Optional command to run on middle button click of media player status indicator.   i3xrocks.action.media-player.right Override command to run on right button click of media player status indicator.   i3xrocks.action.time Override command to run on date time status indicator.   i3xrocks.action.battery Override command to run on battery status indicator.    "},{"id":6,"href":"/de/docs/howtos/add-remove-blocklets/","title":"Change Bar Status indicators","section":"How To","content":"Adding or Removing status indicators #  Finding Status Indicators #  $ apt search i3xrocks- Installing a Status Indicator #  $ sudo apt install i3xrocks-memory $ regolith-look refresh Customization of the i3 bar #  Each status indicator on the bar is managed by a file. The name of the file maps to the position of the status indicator on the bar, e.g. a file\u0026rsquo;s name starting with 10_ mean its corresponding indicator will be positioned before an indicator which has a configuration file starting with 20_. Within each file there is some information that i3xrocks uses to execute a script that ultimately returns the data you see on the bar. Some of the status indicators have configuration parameters that can be adjusted to your liking. For example, if you would prefer that the battery status changes more frequently, the polling interval can be updated. The first thing to do in order to customize the bar is to copy the indicators you wish to see from /usr/share/i3xrocks/conf.d/ to ~/.config/regolith2/i3xrocks/conf.d. Each file in ~/.config/regolith2/i3xrocks/conf.d can be modified as you see fit. To change the order of status indicators on the bar, simply change the name of the files to the sort order you prefer.\nOnce you\u0026rsquo;ve made your changes, refreshing the session should cause the bar to update based on your new configuration.\nFor example, to change the order of the battery and net traffic blocks on the bar and not display notifications, perform the following steps:\n$ ls /usr/share/i3xrocks/conf.d/ 01_setup 30_net-traffic 80_battery 80_rofication 90_time $ mkdir -p ~/.config/regolith2/i3xrocks/conf.d $ cd /usr/share/i3xrocks/conf.d/ $ cp 01_setup ~/.config/regolith2/i3xrocks/conf.d/01_setup $ cp 80_battery ~/.config/regolith2/i3xrocks/conf.d/30_battery $ cp 30_net-traffic ~/.config/regolith2/i3xrocks/conf.d/80_net-traffic $ regolith-look refresh Note: If any block configuration exists in the user directory ~/.config/regolith2/i3xrocks/conf.d, then the defaults in /usr/share/i3xrocks/conf.d/ will be ignored.\nFurther Reading #  The reference page for configurations has more details about the configuration files used with Regolith Linux.\n"}]